wallpaper/console_script.py
wallpaper/__init__.py
wallpaper/wallpaper.py
wallpaper/cubic.py
wallpaper-0.2.2.dist-info/entry_points.txt
wallpaper-0.2.2.dist-info/top_level.txt
wallpaper-0.2.2.dist-info/metadata.json
wallpaper-0.2.2.dist-info/WHEEL
wallpaper-0.2.2.dist-info/RECORD
wallpaper-0.2.2.dist-info/DESCRIPTION.rst
wallpaper-0.2.2.dist-info/METADATA
