Metadata-Version: 2.0
Name: wallpaper
Version: 0.2.2
Summary: Generate wallpapers with Pillow and Palettable.
Home-page: https://github.com/mitakas/wallpaper
Author: Dimitar Dimitrov
Author-email: admin@mitakas.com
License: MIT
Keywords: wallpaper
Platform: UNKNOWN
Classifier: Development Status :: 3 - Alpha
Classifier: License :: OSI Approved :: MIT License
Classifier: Programming Language :: Python :: 2
Classifier: Programming Language :: Python :: 2.7
Classifier: Programming Language :: Python :: 3
Classifier: Programming Language :: Python :: 3.4
Requires-Dist: setuptools
Requires-Dist: Pillow
Requires-Dist: palettable
